<annotation>
	<folder>train</folder>
	<filename>sss (85).jpg</filename>
	<path>E:\YOLOv5\yolov5-5.0\MYbank\images\train\sss (85).jpg</path>
	<source>
		<database>Unknown</database>
	</source>
	<size>
		<width>1023</width>
		<height>656</height>
		<depth>3</depth>
	</size>
	<segmented>0</segmented>
	<object>
		<name>gongshang</name>
		<pose>Unspecified</pose>
		<truncated>0</truncated>
		<difficult>0</difficult>
		<bndbox>
			<xmin>793</xmin>
			<ymin>66</ymin>
			<xmax>973</xmax>
			<ymax>116</ymax>
		</bndbox>
	</object>
	<object>
		<name>number</name>
		<pose>Unspecified</pose>
		<truncated>0</truncated>
		<difficult>0</difficult>
		<bndbox>
			<xmin>92</xmin>
			<ymin>345</ymin>
			<xmax>911</xmax>
			<ymax>421</ymax>
		</bndbox>
	</object>
	<object>
		<name>time</name>
		<pose>Unspecified</pose>
		<truncated>0</truncated>
		<difficult>0</difficult>
		<bndbox>
			<xmin>463</xmin>
			<ymin>479</ymin>
			<xmax>617</xmax>
			<ymax>528</ymax>
		</bndbox>
	</object>
</annotation>
